livestt/__init__.py
livestt/record/__init__.py
livestt/record/record.py
livestt/stt/__init__.py
livestt/stt/stt.py
livestt/wake_word/__init__.py
livestt/wake_word/wake_word.py
livestt-1.0.7.dist-info/METADATA
livestt-1.0.7.dist-info/WHEEL
livestt-1.0.7.dist-info/top_level.txt
livestt-1.0.7.dist-info/RECORD
