Metadata-Version: 2.1
Name: livestt
Version: 1.0.7
Summary: Simple and easy to use realtime speech to text
Author: a3l6
Author-email: <emen3998@gmail.com>
Keywords: python
Classifier: Development Status :: 1 - Planning
Classifier: Intended Audience :: Developers
Classifier: Programming Language :: Python :: 3
Classifier: Operating System :: Unix
Classifier: Operating System :: MacOS :: MacOS X
Classifier: Operating System :: Microsoft :: Windows
Requires-Dist: av ==10.0.0
Requires-Dist: certifi ==2024.2.2
Requires-Dist: charset-normalizer ==3.3.2
Requires-Dist: coloredlogs ==15.0.1
Requires-Dist: ctranslate2 ==3.24.0
Requires-Dist: faster-whisper ==0.10.0
Requires-Dist: filelock ==3.13.1
Requires-Dist: flatbuffers ==23.5.26
Requires-Dist: fsspec ==2024.2.0
Requires-Dist: huggingface-hub ==0.20.3
Requires-Dist: humanfriendly ==10.0
Requires-Dist: idna ==3.6
Requires-Dist: Jinja2 ==3.1.3
Requires-Dist: MarkupSafe ==2.1.5
Requires-Dist: mpmath ==1.3.0
Requires-Dist: networkx ==3.2.1
Requires-Dist: numpy ==1.26.3
Requires-Dist: nvidia-cublas-cu12 ==12.1.3.1
Requires-Dist: nvidia-cuda-cupti-cu12 ==12.1.105
Requires-Dist: nvidia-cuda-nvrtc-cu12 ==12.1.105
Requires-Dist: nvidia-cuda-runtime-cu12 ==12.1.105
Requires-Dist: nvidia-cudnn-cu12 ==8.9.2.26
Requires-Dist: nvidia-cufft-cu12 ==11.0.2.54
Requires-Dist: nvidia-curand-cu12 ==10.3.2.106
Requires-Dist: nvidia-cusolver-cu12 ==11.4.5.107
Requires-Dist: nvidia-cusparse-cu12 ==12.1.0.106
Requires-Dist: nvidia-nccl-cu12 ==2.19.3
Requires-Dist: nvidia-nvjitlink-cu12 ==12.3.101
Requires-Dist: nvidia-nvtx-cu12 ==12.1.105
Requires-Dist: onnxruntime ==1.17.0
Requires-Dist: packaging ==23.2
Requires-Dist: protobuf ==4.25.2
Requires-Dist: pvporcupine ==3.0.2
Requires-Dist: pvrecorder ==1.2.2
Requires-Dist: PyAudio ==0.2.14
Requires-Dist: python-dotenv ==1.0.1
Requires-Dist: PyYAML ==6.0.1
Requires-Dist: regex ==2023.12.25
Requires-Dist: requests ==2.31.0
Requires-Dist: safetensors ==0.4.2
Requires-Dist: sympy ==1.12
Requires-Dist: tokenizers ==0.15.1
Requires-Dist: torch ==2.2.0
Requires-Dist: tqdm ==4.66.1
Requires-Dist: transformers ==4.37.2
Requires-Dist: triton ==2.2.0
Requires-Dist: typing-extensions ==4.9.0
Requires-Dist: urllib3 ==2.2.0
